examples/ex.py
examples/compilation/compiled_image_ecf_test.py
examples/compilation/compiled_wect_test.py
examples/stanford_bunny/bunny_ex.py
pyect/__init__.py
pyect/differentiable_wect.py
pyect/directions.py
pyect/dtypes.py
pyect/image_ecf.py
pyect/tensor_complex.py
pyect/wecfs.py
pyect/wect.py
pyect/preprocessing/__init__.py
pyect/preprocessing/image_processing.py
pyect/preprocessing/mesh_processing.py
pyect-0.1.8.dist-info/licenses/LICENSE
tests/test_wect_triangle.py
pyect-0.1.8.dist-info/METADATA
pyect-0.1.8.dist-info/WHEEL
pyect-0.1.8.dist-info/top_level.txt
pyect-0.1.8.dist-info/RECORD
