Metadata-Version: 2.4
Name: pyect
Version: 0.1.8
Summary: Generalized computation of the weighted Euler characteristic transform using PyTorch.
Author: Alex McCleary, Jack Ruder, Jacob Sriraman
Author-email: Eli Quist <eli.quist@student.montana.edu>
License: MIT
Classifier: Programming Language :: Python :: 3
Classifier: License :: OSI Approved :: MIT License
Classifier: Operating System :: OS Independent
Requires-Python: >=3.8
License-File: LICENSE
Requires-Dist: torch
Requires-Dist: Pillow
Requires-Dist: numpy
Requires-Dist: torchvision
Requires-Dist: trimesh
Dynamic: license-file
